{
  "schemaVersion": 1,
  "id": "mouselock",
  "version": "${version}",
  "name": "MouseLock",
  "description": "MouseLock – a Fabric mod for Minecraft that locks or confines the mouse cursor within the game window, improving control precision and preventing accidental cursor exit.",
  "authors": ["Mirik9724"],
  "license": "MIT",
  "icon": "logo.png",
  "environment": "client",
  "entrypoints": {
    "client": [
      "net.Mirik9724.mouselock.client.MouseLockClient"
    ]
  },
  "contact": {
    "homepage": "https://modrinth.com/mod/mouselock",
    "sources": "https://github.com/Mirik9724/MouseLock/",
    "issues": "https://github.com/Mirik9724/MouseLock/issues"
  },
  "depends": {
    "fabricloader": ">=${loader_version}",
    "fabric": "*",
    "minecraft": ">=${minecraft_version}"
  }
}
